ZeroLogger/ZeroLogger.py
ZeroLogger/__init__.py
ZeroLogger-1.1.3.dist-info/METADATA
ZeroLogger-1.1.3.dist-info/WHEEL
ZeroLogger-1.1.3.dist-info/top_level.txt
ZeroLogger-1.1.3.dist-info/RECORD
