Metadata-Version: 2.1
Name: ZeroLogger
Version: 1.1.3
Summary: My Own Logger Package to throw done/warn/error/critical(error + exit) messages
Home-page: https://github.com/oOHiyoriOo/ZeroLogger
Author: ZéroTwó#5019
Author-email: wolf.sf75@googlemail.com
License: MIT
Platform: UNKNOWN
Requires-Dist: colorama
